nameko_wamp/__init__.py
nameko_wamp/constants.py
nameko_wamp/wamp.py
nameko_wamp/extensions/__init__.py
nameko_wamp/extensions/dependencies.py
nameko_wamp/extensions/entrypoints.py
nameko_wamp/testing/__init__.py
nameko_wamp/testing/utils.py
test/__init__.py
test/conftest.py
test/services.py
test/test_pubsub.py
test/test_rpc.py
nameko_wamp-0.3.0.dist-info/LICENSE
nameko_wamp-0.3.0.dist-info/METADATA
nameko_wamp-0.3.0.dist-info/WHEEL
nameko_wamp-0.3.0.dist-info/top_level.txt
nameko_wamp-0.3.0.dist-info/RECORD
