Metadata-Version: 2.1
Name: nameko-wamp
Version: 0.3.0
Summary: WAMP extension for nameko
Home-page: https://github.com/noisyboiler/nameko_wamp
Author: Simon Harrison
Author-email: noisyboiler@googlemail.com
License: GNU GPLv3
Keywords: WAMP RPC
Platform: UNKNOWN
Classifier: Development Status :: 4 - Beta
Classifier: License :: OSI Approved :: Mozilla Public License 2.0 (MPL 2.0)
Classifier: Programming Language :: Python :: 2.7
Classifier: Programming Language :: Python :: 3.3
Classifier: Programming Language :: Python :: 3.4
Classifier: Programming Language :: Python :: 3.5
Classifier: Programming Language :: Python :: 3.6
Requires-Dist: eventlet (==0.20.1)
Requires-Dist: nameko (==2.5.4)
Requires-Dist: six (==1.10.0)
Requires-Dist: wampy (==0.9.19)
Provides-Extra: dev
Requires-Dist: attrs (==17.4.0) ; extra == 'dev'
Requires-Dist: crossbar (==0.15.0) ; extra == 'dev'
Requires-Dist: autobahn (==0.17.2) ; extra == 'dev'
Requires-Dist: Twisted (==17.9.0) ; extra == 'dev'
Requires-Dist: pytest (==3.1.3) ; extra == 'dev'
Requires-Dist: mock (==1.3.0) ; extra == 'dev'
Requires-Dist: pytest-capturelog (==0.7) ; extra == 'dev'
Requires-Dist: colorlog ; extra == 'dev'
Requires-Dist: flake8 (==3.5.0) ; extra == 'dev'
Requires-Dist: gevent-websocket (==0.10.1) ; extra == 'dev'
Requires-Dist: coverage (>=3.7.1) ; extra == 'dev'
